{
	"cmake" : 
	{
		"generator" : 
		{
			"multiConfig" : false,
			"name" : "Unix Makefiles"
		},
		"paths" : 
		{
			"cmake" : "/usr/bin/cmake",
			"cpack" : "/usr/bin/cpack",
			"ctest" : "/usr/bin/ctest",
			"root" : "/usr/share/cmake"
		},
		"version" : 
		{
			"isDirty" : false,
			"major" : 3,
			"minor" : 26,
			"patch" : 0,
			"string" : "3.26.0",
			"suffix" : ""
		}
	},
	"objects" : 
	[
		{
			"jsonFile" : "codemodel-v2-c6d0622a183344651e4c.json",
			"kind" : "codemodel",
			"version" : 
			{
				"major" : 2,
				"minor" : 5
			}
		},
		{
			"jsonFile" : "cache-v2-448cd6c57d999b8ac710.json",
			"kind" : "cache",
			"version" : 
			{
				"major" : 2,
				"minor" : 0
			}
		},
		{
			"jsonFile" : "cmakeFiles-v1-22cd267b8a63100ee70b.json",
			"kind" : "cmakeFiles",
			"version" : 
			{
				"major" : 1,
				"minor" : 0
			}
		}
	],
	"reply" : 
	{
		"cache-v2" : 
		{
			"jsonFile" : "cache-v2-448cd6c57d999b8ac710.json",
			"kind" : "cache",
			"version" : 
			{
				"major" : 2,
				"minor" : 0
			}
		},
		"cmakeFiles-v1" : 
		{
			"jsonFile" : "cmakeFiles-v1-22cd267b8a63100ee70b.json",
			"kind" : "cmakeFiles",
			"version" : 
			{
				"major" : 1,
				"minor" : 0
			}
		},
		"codemodel-v2" : 
		{
			"jsonFile" : "codemodel-v2-c6d0622a183344651e4c.json",
			"kind" : "codemodel",
			"version" : 
			{
				"major" : 2,
				"minor" : 5
			}
		}
	}
}
